{
  "HOMBU 9": {
    "Capitolo Asti": {
      "Settore Fukyo": [
        "AURORA", "COLLINE", "KANSAI", "SOLE", "TORREPREZIOSA", "VITTORIA"
      ],
      "Settore Invictus": [
        "ALFIERI", "CESARE PAVESE", "RINASCIMENTO"
      ]
    },
    "Capitolo Casale/Crescentino": {
      "Settore Casale": [
        "DHARMA", "FENICE", "LEONI", "LAGO", "MAZZINI"
      ],
      "Settore Crescentino": [
        "AIRONE", "CASALBORGONE", "CAVAGNOLO", "GIOTTO", "LAURIANO", "VESPUCCI"
      ]
    }
  }
}
